pysolver_view/__init__.py
pysolver_view/nonlinear_system.py
pysolver_view/nonlinear_system_problems.py
pysolver_view/numerical_differentiation.py
pysolver_view/optimization.py
pysolver_view/optimization_problems.py
pysolver_view/optimization_wrappers.py
pysolver_view/pysolver_utilities.py
pysolver_view-0.6.8.dist-info/LICENSE.md
pysolver_view-0.6.8.dist-info/METADATA
pysolver_view-0.6.8.dist-info/WHEEL
pysolver_view-0.6.8.dist-info/RECORD
